README.md
setup.py
congaworkerservice/__init__.py
congaworkerservice/congaworkerservice.py
congaworkerservice.egg-info/PKG-INFO
congaworkerservice.egg-info/SOURCES.txt
congaworkerservice.egg-info/dependency_links.txt
congaworkerservice.egg-info/requires.txt
congaworkerservice.egg-info/top_level.txt