Metadata-Version: 2.1
Name: congaworkerservice
Version: 0.0.5
Summary: A package to interact with queue message broker
Home-page: https://github.com/nmarkovic-conga/conga-worker-service/
Author: Nikola Markovic
Author-email: nmarkovic@conga.com
License: UNKNOWN
Platform: UNKNOWN
Classifier: Programming Language :: Python :: 3.9
Classifier: License :: OSI Approved :: GNU General Public License v3 (GPLv3)
